sciunivariate/__init__.py
sciunivariate/sciunivariate.py
sciunivariate-0.0.1.dist-info/LICENSE
sciunivariate-0.0.1.dist-info/METADATA
sciunivariate-0.0.1.dist-info/WHEEL
sciunivariate-0.0.1.dist-info/top_level.txt
sciunivariate-0.0.1.dist-info/RECORD
