Metadata-Version: 2.1
Name: sciunivariate
Version: 0.0.1
Summary: A small example package
Home-page: https://github.com/gurditsingh/FirstPython
Author: gurdit singh
Author-email: gurdit.singh@example.com
License: UNKNOWN
Platform: UNKNOWN
Classifier: Programming Language :: Python :: 3
Classifier: License :: OSI Approved :: MIT License
Classifier: Operating System :: OS Independent
Requires-Dist: texttable (>=1.6.1)
